sqladmin/__init__.py
sqladmin/_queries.py
sqladmin/_types.py
sqladmin/_validators.py
sqladmin/ajax.py
sqladmin/application.py
sqladmin/authentication.py
sqladmin/exceptions.py
sqladmin/fields.py
sqladmin/formatters.py
sqladmin/forms.py
sqladmin/helpers.py
sqladmin/models.py
sqladmin/pagination.py
sqladmin/widgets.py
kessel_sqladmin-0.5.0.dist-info/METADATA
kessel_sqladmin-0.5.0.dist-info/WHEEL
kessel_sqladmin-0.5.0.dist-info/licenses/LICENSE.md
kessel_sqladmin-0.5.0.dist-info/RECORD
