Metadata-Version: 2.1
Name: kessel_sqladmin
Version: 0.5.0
Summary: SQLAlchemy admin for FastAPI and Starlette
Project-URL: Documentation, https://aminalaee.dev/sqladmin
Project-URL: Issues, https://github.com/aminalaee/sqladmin/issues
Project-URL: Source, https://github.com/aminalaee/sqladmin
Author-email: Thibault Lebrun <thibaultlebrun@live.fr>
Keywords: admin,fastapi,sqlalchemy,starlette
Classifier: Development Status :: 3 - Alpha
Classifier: Environment :: Web Environment
Classifier: Intended Audience :: Developers
Classifier: License :: OSI Approved :: BSD License
Classifier: Operating System :: OS Independent
Classifier: Programming Language :: Python
Classifier: Programming Language :: Python :: 3.7
Classifier: Programming Language :: Python :: 3.8
Classifier: Programming Language :: Python :: 3.9
Classifier: Programming Language :: Python :: 3.10
Classifier: Topic :: Internet :: WWW/HTTP
Requires-Python: >=3.7
Requires-Dist: sqlalchemy<1.5,>=1.4
Requires-Dist: starlette[full]
Requires-Dist: typing-extensions>=4.0; python_version < '3.8'
Requires-Dist: wtforms<4,>=3
